xautodl/__init__.py
xautodl/config_utils/__init__.py
xautodl/config_utils/args_utils.py
xautodl/config_utils/attention_args.py
xautodl/config_utils/basic_args.py
xautodl/config_utils/cls_init_args.py
xautodl/config_utils/cls_kd_args.py
xautodl/config_utils/config_utils.py
xautodl/config_utils/pruning_args.py
xautodl/config_utils/random_baseline.py
xautodl/config_utils/search_args.py
xautodl/config_utils/search_single_args.py
xautodl/config_utils/share_args.py
xautodl/datasets/DownsampledImageNet.py
xautodl/datasets/LandmarkDataset.py
xautodl/datasets/SearchDatasetWrap.py
xautodl/datasets/__init__.py
xautodl/datasets/get_dataset_with_transform.py
xautodl/datasets/math_base_funcs.py
xautodl/datasets/math_core.py
xautodl/datasets/math_dynamic_funcs.py
xautodl/datasets/math_dynamic_generator.py
xautodl/datasets/math_static_funcs.py
xautodl/datasets/synthetic_core.py
xautodl/datasets/synthetic_env.py
xautodl/datasets/synthetic_utils.py
xautodl/datasets/test_utils.py
xautodl/datasets/landmark_utils/__init__.py
xautodl/datasets/landmark_utils/point_meta.py
xautodl/log_utils/__init__.py
xautodl/log_utils/logger.py
xautodl/log_utils/meter.py
xautodl/log_utils/pickle_wrap.py
xautodl/log_utils/time_utils.py
xautodl/models/CifarDenseNet.py
xautodl/models/CifarResNet.py
xautodl/models/CifarWideResNet.py
xautodl/models/ImageNet_MobileNetV2.py
xautodl/models/ImageNet_ResNet.py
xautodl/models/SharedUtils.py
xautodl/models/__init__.py
xautodl/models/cell_operations.py
xautodl/models/clone_weights.py
xautodl/models/initialization.py
xautodl/models/cell_infers/__init__.py
xautodl/models/cell_infers/cells.py
xautodl/models/cell_infers/nasnet_cifar.py
xautodl/models/cell_infers/tiny_network.py
xautodl/models/cell_searchs/__init__.py
xautodl/models/cell_searchs/_test_module.py
xautodl/models/cell_searchs/generic_model.py
xautodl/models/cell_searchs/genotypes.py
xautodl/models/cell_searchs/search_cells.py
xautodl/models/cell_searchs/search_model_darts.py
xautodl-1.0.0.dist-info/LICENSE.md
xautodl-1.0.0.dist-info/METADATA
xautodl-1.0.0.dist-info/WHEEL
xautodl-1.0.0.dist-info/top_level.txt
xautodl-1.0.0.dist-info/RECORD
