Metadata-Version: 2.1
Name: xautodl
Version: 1.0.0
Summary: Automated Deep Learning Package
Home-page: https://github.com/D-X-Y/AutoDL-Projects
Author: Xuanyi Dong
Author-email: dongxuanyi888@gmail.com
License: MIT Licence
Keywords: NAS Dataset API DeepLearning
Platform: UNKNOWN
Classifier: Programming Language :: Python
Classifier: Programming Language :: Python :: 3
Classifier: Topic :: Database
Classifier: Topic :: Scientific/Engineering :: Artificial Intelligence
Classifier: License :: OSI Approved :: MIT License
Requires-Python: >=3.6
Requires-Dist: numpy (<=1.19.5,>=1.16.5)
Requires-Dist: pyyaml (>=5.0.0)
Requires-Dist: fvcore
